WebLurker/WebLurker.py
WebLurker/__init__.py
WebLurker/cache.py
WebLurker/core.py
WebLurker/exception.py
WebLurker/util.py
WebLurker-0.3.0.dist-info/DESCRIPTION.rst
WebLurker-0.3.0.dist-info/METADATA
WebLurker-0.3.0.dist-info/RECORD
WebLurker-0.3.0.dist-info/WHEEL
WebLurker-0.3.0.dist-info/metadata.json
WebLurker-0.3.0.dist-info/top_level.txt
