Metadata-Version: 2.0
Name: WebLurker
Version: 0.3.0
Summary: Simple and easy to use web crawler
Home-page: https://javierlunamolina.wordpress.com/projects/weblurker/
Author: Javier Luna Molina
Author-email: javierlunamolina@gmail.com
License: http://www.binpress.com/license/view/l/72ebdc04171cf6ec2b1b03c668004b87
Platform: any
Classifier: Programming Language :: Python :: 3
Classifier: Development Status :: 1 - Planning
Classifier: Natural Language :: English
Classifier: Intended Audience :: Developers
Classifier: License :: Other/Proprietary License
Classifier: Operating System :: OS Independent
Classifier: Topic :: Software Development :: Libraries :: Python Modules
Classifier: Topic :: Internet :: WWW/HTTP
Requires-Dist: requests (>=2.9.1)
Requires-Dist: selenium (>=-2.53.1)
Provides-Extra: testing
Requires-Dist: pytest; extra == 'testing'
